kdm_sdk/__init__.py
kdm_sdk/client.py
kdm_sdk/facilities.py
kdm_sdk/query.py
kdm_sdk/results.py
kdm_sdk/templates/__init__.py
kdm_sdk/templates/base.py
kdm_sdk/templates/builder.py
kdm_sdk/templates/loaders.py
kdm_sdk-0.2.4.dist-info/licenses/LICENSE
kdm_sdk-0.2.4.dist-info/METADATA
kdm_sdk-0.2.4.dist-info/WHEEL
kdm_sdk-0.2.4.dist-info/top_level.txt
kdm_sdk-0.2.4.dist-info/RECORD
