Metadata-Version: 2.4
Name: kdm-sdk
Version: 0.2.4
Summary: KDM (K-water Data Model) SDK for water resource data access
Author: K-water
Author-email: K-water <kdm-sdk@example.com>
License: MIT
Project-URL: Homepage, https://github.com/kwatermywater/kdm-sdk
Project-URL: Repository, https://github.com/kwatermywater/kdm-sdk
Project-URL: Issues, https://github.com/kwatermywater/kdm-sdk/issues
Project-URL: Documentation, https://github.com/kwatermywater/kdm-sdk/blob/main/docs/DATA_GUIDE.md
Keywords: kdm,k-water,dam,water,hydrology,water-resources
Classifier: Development Status :: 4 - Beta
Classifier: Intended Audience :: Developers
Classifier: Intended Audience :: Science/Research
Classifier: License :: OSI Approved :: MIT License
Classifier: Programming Language :: Python :: 3
Classifier: Programming Language :: Python :: 3.10
Classifier: Programming Language :: Python :: 3.11
Classifier: Programming Language :: Python :: 3.12
Classifier: Topic :: Scientific/Engineering :: Hydrology
Classifier: Topic :: Software Development :: Libraries :: Python Modules
Requires-Python: >=3.10
License-File: LICENSE
Requires-Dist: pandas>=2.0.0
Requires-Dist: requests>=2.31.0
Requires-Dist: python-dateutil>=2.8.2
Requires-Dist: mcp>=0.1.0
Requires-Dist: pyyaml>=6.0
Provides-Extra: dev
Requires-Dist: pytest>=7.4.0; extra == "dev"
Requires-Dist: pytest-asyncio>=0.21.0; extra == "dev"
Requires-Dist: black>=23.0.0; extra == "dev"
Requires-Dist: mypy>=1.5.0; extra == "dev"
Dynamic: author
Dynamic: license-file
Dynamic: requires-python
